sdrcap/__init__.py
sdrcap/recorders/__init__.py
sdrcap/recorders/csv_recorder.py
sdrcap/recorders/hdf5_recorder.py
sdrcap/recorders/recorder.py
sdrcap/rtl_interface.py
sdrcap-0.0.1.dist-info/LICENSE
sdrcap-0.0.1.dist-info/METADATA
sdrcap-0.0.1.dist-info/WHEEL
sdrcap-0.0.1.dist-info/RECORD
