Metadata-Version: 2.1
Name: sdrcap
Version: 0.0.1
Summary: A software defined radio capture library in python
License: GPLV3
Keywords: sdr,recording
Author: chris
Author-email: kosik.chris.j@gmail.com
Requires-Python: >=3.12,<4.0
Classifier: License :: Other/Proprietary License
Classifier: Programming Language :: Python :: 3
Classifier: Programming Language :: Python :: 3.12
Requires-Dist: black (>=24.8.0,<25.0.0)
Requires-Dist: datetime (>=5.5,<6.0)
Requires-Dist: h5py (>=3.11.0,<4.0.0)
Requires-Dist: matplotlib (>=3.9.2,<4.0.0)
Requires-Dist: numpy (>=2.1.0,<3.0.0)
Requires-Dist: pandas (>=2.2.2,<3.0.0)
Requires-Dist: pdoc (>=14.6.0,<15.0.0)
Requires-Dist: pylint (>=3.2.6,<4.0.0)
Requires-Dist: pyrtlsdr[lib] (>=0.3.0,<0.4.0)
Requires-Dist: setuptools (>=73.0.1,<74.0.0)
Requires-Dist: toml (>=0.10.2,<0.11.0)
Requires-Dist: twine (>=5.1.1,<6.0.0)
Requires-Dist: wheel (>=0.44.0,<0.45.0)
